README.rst
setup.py
scConnect/__init__.py
scConnect/app.py
scConnect/connect.py
scConnect/database.py
scConnect/genecall.py
scConnect/graph.py
scConnect/molecules.py
scConnect/tools.py
scConnect.egg-info/PKG-INFO
scConnect.egg-info/SOURCES.txt
scConnect.egg-info/dependency_links.txt
scConnect.egg-info/requires.txt
scConnect.egg-info/top_level.txt
scConnect/assets/app.css
scConnect/assets/favicon.ico
scConnect/assets/graph.yaml
scConnect/assets/logo.png
scConnect/data/GTP_tables/license.txt
scConnect/data/GTP_tables/2018-4/interactions.csv
scConnect/data/GTP_tables/2018-4/ligands.csv
scConnect/data/GTP_tables/2018-4/peptides.csv
scConnect/data/GTP_tables/2018-4/targets_and_families.csv
scConnect/data/GTP_tables/2019-5/interactions.csv
scConnect/data/GTP_tables/2019-5/ligands.csv
scConnect/data/GTP_tables/2019-5/peptides.csv
scConnect/data/GTP_tables/2019-5/targets_and_families.csv
scConnect/data/GTP_tables/2020-5/interactions.csv
scConnect/data/GTP_tables/2020-5/ligands.csv
scConnect/data/GTP_tables/2020-5/peptides.csv
scConnect/data/GTP_tables/2020-5/targets_and_families.csv
scConnect/data/GTP_tables_clean/2018-4/interactions.csv
scConnect/data/GTP_tables_clean/2018-4/ligands.csv
scConnect/data/GTP_tables_clean/2018-4/peptides.csv
scConnect/data/GTP_tables_clean/2018-4/targets.csv
scConnect/data/GTP_tables_clean/2019-5/interactions.csv
scConnect/data/GTP_tables_clean/2019-5/ligands.csv
scConnect/data/GTP_tables_clean/2019-5/peptides.csv
scConnect/data/GTP_tables_clean/2019-5/targets.csv
scConnect/data/GTP_tables_clean/2020-5/interactions.csv
scConnect/data/GTP_tables_clean/2020-5/ligands.csv
scConnect/data/GTP_tables_clean/2020-5/peptides.csv
scConnect/data/GTP_tables_clean/2020-5/targets.csv
scConnect/data/Gene_annotation/2018-4/interactions.csv
scConnect/data/Gene_annotation/2018-4/drerio/ligands.csv
scConnect/data/Gene_annotation/2018-4/drerio/molecule_ligands.csv
scConnect/data/Gene_annotation/2018-4/drerio/peptide_ligands.csv
scConnect/data/Gene_annotation/2018-4/drerio/receptors.csv
scConnect/data/Gene_annotation/2018-4/hsapiens/ligands.csv
scConnect/data/Gene_annotation/2018-4/hsapiens/molecule_ligands.csv
